dococtopy/__init__.py
dococtopy/__main__.py
dococtopy/_version.py
dococtopy/adapters/__init__.py
dococtopy/adapters/base.py
dococtopy/adapters/python/__init__.py
dococtopy/adapters/python/adapter.py
dococtopy/adapters/python/parser.py
dococtopy/cli/__init__.py
dococtopy/cli/commands.py
dococtopy/cli/main.py
dococtopy/core/__init__.py
dococtopy/core/cache.py
dococtopy/core/config.py
dococtopy/core/discovery.py
dococtopy/core/engine.py
dococtopy/core/findings.py
dococtopy/playground/__init__.py
dococtopy/playground/tui.py
dococtopy/remediation/__init__.py
dococtopy/remediation/diff.py
dococtopy/remediation/engine.py
dococtopy/remediation/indentation.py
dococtopy/remediation/interactive.py
dococtopy/remediation/llm.py
dococtopy/remediation/prompts.py
dococtopy/remediation/signatures.py
dococtopy/remediation/validation.py
dococtopy/reporters/__init__.py
dococtopy/reporters/base.py
dococtopy/reporters/console.py
dococtopy/reporters/json_reporter.py
dococtopy/reporters/sarif.py
dococtopy/rules/__init__.py
dococtopy/rules/base.py
dococtopy/rules/registry.py
dococtopy/rules/python/__init__.py
dococtopy/rules/python/ast_utils.py
dococtopy/rules/python/context_specific.py
dococtopy/rules/python/formatting.py
dococtopy/rules/python/google_style.py
dococtopy/rules/python/missing_docstrings.py
dococtopy-0.2.1.dist-info/METADATA
dococtopy-0.2.1.dist-info/WHEEL
dococtopy-0.2.1.dist-info/entry_points.txt
dococtopy-0.2.1.dist-info/licenses/LICENSE
dococtopy-0.2.1.dist-info/RECORD
