Metadata-Version: 2.4
Name: dococtopy
Version: 0.2.1
Summary: A language-agnostic docstyle compliance & remediation tool
Author-email: Michael <your-email@example.com>
Maintainer-email: Michael <your-email@example.com>
License: MIT
License-File: LICENSE
Keywords: ai,compliance,docstring,documentation,linting,llm
Classifier: Development Status :: 3 - Alpha
Classifier: Intended Audience :: Developers
Classifier: License :: OSI Approved :: MIT License
Classifier: Operating System :: OS Independent
Classifier: Programming Language :: Python :: 3
Classifier: Programming Language :: Python :: 3.9
Classifier: Programming Language :: Python :: 3.10
Classifier: Programming Language :: Python :: 3.11
Classifier: Programming Language :: Python :: 3.12
Classifier: Topic :: Software Development :: Documentation
Classifier: Topic :: Software Development :: Libraries :: Python Modules
Classifier: Topic :: Software Development :: Quality Assurance
Classifier: Topic :: Text Processing :: Markup
Requires-Python: >=3.10
Requires-Dist: ast-tools>=0.1.8
Requires-Dist: docstring-parser>=0.17.0
Requires-Dist: pathspec>=0.12.1
Requires-Dist: pydantic>=2.11.7
Requires-Dist: rich>=14.1.0
Requires-Dist: tomli-w>=1.0.0
Requires-Dist: tomli>=2.0.0; python_version < '3.11'
Requires-Dist: typer>=0.16.1
Provides-Extra: llm
Requires-Dist: anthropic>=0.66.0; extra == 'llm'
Requires-Dist: dspy-ai>=3.0.3; extra == 'llm'
Requires-Dist: openai>=1.107.0; extra == 'llm'
